MANIFEST.in
README.md
setup.cfg
setup.py
govuk_template/VERSION.py
govuk_template/__init__.py
govuk_template.egg-info/PKG-INFO
govuk_template.egg-info/SOURCES.txt
govuk_template.egg-info/dependency_links.txt
govuk_template.egg-info/requires.txt
govuk_template.egg-info/top_level.txt
govuk_template/assets/images/apple-touch-icon-120x120.png
govuk_template/assets/images/apple-touch-icon-152x152.png
govuk_template/assets/images/apple-touch-icon-60x60.png
govuk_template/assets/images/apple-touch-icon-76x76.png
govuk_template/assets/images/favicon.ico
govuk_template/assets/images/gov.uk_logotype_crown.png
govuk_template/assets/images/gov.uk_logotype_crown_invert.png
govuk_template/assets/images/gov.uk_logotype_crown_invert_trans.png
govuk_template/assets/images/opengraph-image.png
govuk_template/assets/javascripts/govuk-template.js
govuk_template/assets/javascripts/ie.js
govuk_template/assets/javascripts/vendor/goog/webfont-debug.js
govuk_template/assets/stylesheets/fonts-ie8.css
govuk_template/assets/stylesheets/fonts.css
govuk_template/assets/stylesheets/govuk-template-ie6.css
govuk_template/assets/stylesheets/govuk-template-ie7.css
govuk_template/assets/stylesheets/govuk-template-ie8.css
govuk_template/assets/stylesheets/govuk-template-print.css
govuk_template/assets/stylesheets/govuk-template.css
govuk_template/assets/stylesheets/external-links/external-link-24x24.png
govuk_template/assets/stylesheets/external-links/external-link-black-12x12.png
govuk_template/assets/stylesheets/external-links/external-link-black-24x24.png
govuk_template/assets/stylesheets/external-links/external-link.png
govuk_template/assets/stylesheets/fonts/NTA-Bold-20130221.eot
govuk_template/assets/stylesheets/fonts/NTA-Bold-20130221.woff
govuk_template/assets/stylesheets/fonts/NTA-Light-20130221.eot
govuk_template/assets/stylesheets/fonts/NTA-Light-20130221.woff
govuk_template/assets/stylesheets/fonts/NTATabularNumbers-Bold.eot
govuk_template/assets/stylesheets/fonts/NTATabularNumbers-Bold.woff
govuk_template/assets/stylesheets/fonts/NTATabularNumbers-Light.eot
govuk_template/assets/stylesheets/fonts/NTATabularNumbers-Light.woff
govuk_template/assets/stylesheets/images/close.png
