Metadata-Version: 1.1
Name: govuk-template
Version: 0.2.41
Summary: The GOV.UK template for python
Home-page: https://github.com/LandRegistry/python-govuk-template
Author: Ramin Vazir <ramin.vazir@digital.landregistry.gov.uk>,            Michael Allen <michael@michaelallen.io>
Author-email: UNKNOWN
License: MIT
Platform: UNKNOWN
Classifier: Development Status :: 1 - Planning
Classifier: Intended Audience :: Developers
Classifier: Natural Language :: English
Classifier: License :: OSI Approved :: MIT License
Classifier: Operating System :: OS Independent
Classifier: Programming Language :: Python
Classifier: Programming Language :: Python :: 3.4
Classifier: Topic :: Software Development :: Libraries :: Python Modules
Classifier: Topic :: Software Development :: User Interfaces
